{
"meta":{"test_sets":[],"test_metrics":[],"learn_metrics":[{"best_value":"Min","name":"RMSE"}],"launch_mode":"Train","parameters":"","iteration_count":200,"learn_sets":["learn"],"name":"experiment"},
"iterations":[
{"learn":[14.17310683],"iteration":0,"passed_time":0.0005983818834,"remaining_time":0.1190779948},
{"learn":[13.28240619],"iteration":1,"passed_time":0.001005142086,"remaining_time":0.09950906647},
{"learn":[12.60488407],"iteration":2,"passed_time":0.001388370663,"remaining_time":0.09116967355},
{"learn":[11.91665291],"iteration":3,"passed_time":0.001767498065,"remaining_time":0.08660740516},
{"learn":[11.27092657],"iteration":4,"passed_time":0.002129490841,"remaining_time":0.0830501428},
{"learn":[10.78443789],"iteration":5,"passed_time":0.002560762964,"remaining_time":0.08279800252},
{"learn":[10.20531253],"iteration":6,"passed_time":0.003033066779,"remaining_time":0.08362598405},
{"learn":[9.743931476],"iteration":7,"passed_time":0.003511381903,"remaining_time":0.08427316566},
{"learn":[9.259855765],"iteration":8,"passed_time":0.003978822159,"remaining_time":0.08443944805},
{"learn":[8.967597746],"iteration":9,"passed_time":0.004531686127,"remaining_time":0.08610203642},
{"learn":[8.640795672],"iteration":10,"passed_time":0.004989678251,"remaining_time":0.08573174449},
{"learn":[8.334049182],"iteration":11,"passed_time":0.005433774907,"remaining_time":0.08512914021},
{"learn":[8.061925049],"iteration":12,"passed_time":0.005939299214,"remaining_time":0.08543453485},
{"learn":[7.835464536],"iteration":13,"passed_time":0.006372852376,"remaining_time":0.08466789586},
{"learn":[7.625549978],"iteration":14,"passed_time":0.006882574283,"remaining_time":0.08488508282},
{"learn":[7.440105014],"iteration":15,"passed_time":0.007369271427,"remaining_time":0.08474662141},
{"learn":[7.222216685],"iteration":16,"passed_time":0.007860672067,"remaining_time":0.08461782284},
{"learn":[7.054854836],"iteration":17,"passed_time":0.008335569329,"remaining_time":0.08428186766},
{"learn":[6.901149553],"iteration":18,"passed_time":0.008852973228,"remaining_time":0.08433621865},
{"learn":[6.754326046],"iteration":19,"passed_time":0.00931539565,"remaining_time":0.08383856085},
{"learn":[6.644433767],"iteration":20,"passed_time":0.009819813347,"remaining_time":0.08370221853},
{"learn":[6.553049047],"iteration":21,"passed_time":0.01035282421,"remaining_time":0.08376375956},
{"learn":[6.468389231],"iteration":22,"passed_time":0.01097388567,"remaining_time":0.0844512071},
{"learn":[6.381168323],"iteration":23,"passed_time":0.01185660989,"remaining_time":0.08694847251},
{"learn":[6.287027135],"iteration":24,"passed_time":0.01237023402,"remaining_time":0.08659163813},
{"learn":[6.192900524],"iteration":25,"passed_time":0.01281838332,"remaining_time":0.08578456529},
{"learn":[6.109534735],"iteration":26,"passed_time":0.01332735377,"remaining_time":0.08539378528},
{"learn":[6.038153262],"iteration":27,"passed_time":0.0138343016,"remaining_time":0.08498213839},
{"learn":[5.985150859],"iteration":28,"passed_time":0.01429559009,"remaining_time":0.0842946864},
{"learn":[5.922471112],"iteration":29,"passed_time":0.01474142107,"remaining_time":0.08353471939},
{"learn":[5.879454742],"iteration":30,"passed_time":0.01527403178,"remaining_time":0.08326810875},
{"learn":[5.842252478],"iteration":31,"passed_time":0.01572774274,"remaining_time":0.08257064939},
{"learn":[5.80182112],"iteration":32,"passed_time":0.01626422161,"remaining_time":0.08230681845},
{"learn":[5.760199323],"iteration":33,"passed_time":0.01674120706,"remaining_time":0.08173648155},
{"learn":[5.72728368],"iteration":34,"passed_time":0.01725440244,"remaining_time":0.08134218291},
{"learn":[5.698989738],"iteration":35,"passed_time":0.01775278793,"remaining_time":0.08087381169},
{"learn":[5.670514289],"iteration":36,"passed_time":0.01821355381,"remaining_time":0.08023808842},
{"learn":[5.638469371],"iteration":37,"passed_time":0.01864438368,"remaining_time":0.07948395147},
{"learn":[5.62256276],"iteration":38,"passed_time":0.01923668386,"remaining_time":0.07941297698},
{"learn":[5.599231189],"iteration":39,"passed_time":0.01974426712,"remaining_time":0.07897706847},
{"learn":[5.578173984],"iteration":40,"passed_time":0.02016373615,"remaining_time":0.07819595237},
{"learn":[5.554412377],"iteration":41,"passed_time":0.02066806578,"remaining_time":0.07775129506},
{"learn":[5.53570604],"iteration":42,"passed_time":0.02123756233,"remaining_time":0.07754179734},
{"learn":[5.512357011],"iteration":43,"passed_time":0.0217504424,"remaining_time":0.07711520487},
{"learn":[5.493378859],"iteration":44,"passed_time":0.0223481024,"remaining_time":0.07697679715},
{"learn":[5.473334625],"iteration":45,"passed_time":0.02280006682,"remaining_time":0.07633065848},
{"learn":[5.451930691],"iteration":46,"passed_time":0.0232840487,"remaining_time":0.0757970096},
{"learn":[5.437692262],"iteration":47,"passed_time":0.02374852782,"remaining_time":0.07520367143},
{"learn":[5.425964817],"iteration":48,"passed_time":0.02424516903,"remaining_time":0.07471470456},
{"learn":[5.412462404],"iteration":49,"passed_time":0.02474948902,"remaining_time":0.07424846706},
{"learn":[5.395591629],"iteration":50,"passed_time":0.02527081025,"remaining_time":0.07383040641},
{"learn":[5.390233685],"iteration":51,"passed_time":0.02560632344,"remaining_time":0.07287953594},
{"learn":[5.376251384],"iteration":52,"passed_time":0.02598897669,"remaining_time":0.07208263347},
{"learn":[5.36471932],"iteration":53,"passed_time":0.02647084081,"remaining_time":0.07156931035},
{"learn":[5.350628071],"iteration":54,"passed_time":0.02701057009,"remaining_time":0.07120968478},
{"learn":[5.342832742],"iteration":55,"passed_time":0.02757678602,"remaining_time":0.07091173549},
{"learn":[5.337239207],"iteration":56,"passed_time":0.02814445376,"remaining_time":0.07060801557},
{"learn":[5.32207017],"iteration":57,"passed_time":0.02860862175,"remaining_time":0.07004179808},
{"learn":[5.308641875],"iteration":58,"passed_time":0.02916146547,"remaining_time":0.06969095986},
{"learn":[5.300518705],"iteration":59,"passed_time":0.02962590827,"remaining_time":0.0691271193},
{"learn":[5.291728381],"iteration":60,"passed_time":0.03019074568,"remaining_time":0.06879530573},
{"learn":[5.276965842],"iteration":61,"passed_time":0.03068394878,"remaining_time":0.06829653116},
{"learn":[5.264221967],"iteration":62,"passed_time":0.03128455481,"remaining_time":0.06803149221},
{"learn":[5.252071767],"iteration":63,"passed_time":0.0317894768,"remaining_time":0.0675526382},
{"learn":[5.239438578],"iteration":64,"passed_time":0.03224956194,"remaining_time":0.06697985941},
{"learn":[5.232530341],"iteration":65,"passed_time":0.03280658397,"remaining_time":0.06660730685},
{"learn":[5.219607317],"iteration":66,"passed_time":0.03328483706,"remaining_time":0.06607288552},
{"learn":[5.211819012],"iteration":67,"passed_time":0.03370534006,"remaining_time":0.06542801307},
{"learn":[5.205180435],"iteration":68,"passed_time":0.03415604906,"remaining_time":0.0648469917},
{"learn":[5.204315467],"iteration":69,"passed_time":0.03453277393,"remaining_time":0.06413229445},
{"learn":[5.199528961],"iteration":70,"passed_time":0.03498036559,"remaining_time":0.06355587551},
{"learn":[5.19263964],"iteration":71,"passed_time":0.03550731887,"remaining_time":0.06312412243},
{"learn":[5.189581282],"iteration":72,"passed_time":0.03593256682,"remaining_time":0.06251282173},
{"learn":[5.180377586],"iteration":73,"passed_time":0.03635225827,"remaining_time":0.0618970884},
{"learn":[5.172330844],"iteration":74,"passed_time":0.03681064444,"remaining_time":0.06135107406},
{"learn":[5.15651679],"iteration":75,"passed_time":0.03725485005,"remaining_time":0.06078422903},
{"learn":[5.1503469],"iteration":76,"passed_time":0.03773852274,"remaining_time":0.06028361424},
{"learn":[5.145612778],"iteration":77,"passed_time":0.03822314712,"remaining_time":0.05978492241},
{"learn":[5.138740173],"iteration":78,"passed_time":0.03867020813,"remaining_time":0.05922905295},
{"learn":[5.134191137],"iteration":79,"passed_time":0.03915065419,"remaining_time":0.05872598128},
{"learn":[5.125336094],"iteration":80,"passed_time":0.03958682201,"remaining_time":0.05815841752},
{"learn":[5.120051343],"iteration":81,"passed_time":0.0399887418,"remaining_time":0.05754477478},
{"learn":[5.114080057],"iteration":82,"passed_time":0.0404869833,"remaining_time":0.05707201261},
{"learn":[5.10337737],"iteration":83,"passed_time":0.04094454024,"remaining_time":0.05654246033},
{"learn":[5.097768916],"iteration":84,"passed_time":0.04138128403,"remaining_time":0.05598644309},
{"learn":[5.09308593],"iteration":85,"passed_time":0.04185829262,"remaining_time":0.05548657394},
{"learn":[5.088210334],"iteration":86,"passed_time":0.04230984018,"remaining_time":0.05495416023},
{"learn":[5.082384686],"iteration":87,"passed_time":0.04276996035,"remaining_time":0.05443449499},
{"learn":[5.074325489],"iteration":88,"passed_time":0.04320153363,"remaining_time":0.05388056442},
{"learn":[5.06917087],"iteration":89,"passed_time":0.04364550173,"remaining_time":0.05334450211},
{"learn":[5.06323426],"iteration":90,"passed_time":0.04414233642,"remaining_time":0.05287378759},
{"learn":[5.058370274],"iteration":91,"passed_time":0.04462302258,"remaining_time":0.05238354825},
{"learn":[5.057937981],"iteration":92,"passed_time":0.04503428283,"remaining_time":0.05181363723},
{"learn":[5.052311155],"iteration":93,"passed_time":0.04550675217,"remaining_time":0.05131612478},
{"learn":[5.049056031],"iteration":94,"passed_time":0.0459516276,"remaining_time":0.05078864103},
{"learn":[5.037258014],"iteration":95,"passed_time":0.04644738076,"remaining_time":0.05031799582},
{"learn":[5.03203217],"iteration":96,"passed_time":0.04705373293,"remaining_time":0.04996427312},
{"learn":[5.018048941],"iteration":97,"passed_time":0.04745786305,"remaining_time":0.04939491868},
{"learn":[5.013624225],"iteration":98,"passed_time":0.04792736868,"remaining_time":0.04889559835},
{"learn":[5.008636665],"iteration":99,"passed_time":0.04840163919,"remaining_time":0.04840163919},
{"learn":[5.003585993],"iteration":100,"passed_time":0.04887393979,"remaining_time":0.04790613901},
{"learn":[5.003005207],"iteration":101,"passed_time":0.04931957664,"remaining_time":0.0473854756},
{"learn":[4.998886849],"iteration":102,"passed_time":0.04973308321,"remaining_time":0.04683601041},
{"learn":[4.99450202],"iteration":103,"passed_time":0.05012306073,"remaining_time":0.04626744068},
{"learn":[4.987820643],"iteration":104,"passed_time":0.05057971419,"remaining_time":0.04576259855},
{"learn":[4.984739586],"iteration":105,"passed_time":0.05095877602,"remaining_time":0.04518985798},
{"learn":[4.981804697],"iteration":106,"passed_time":0.05144259977,"remaining_time":0.04471179233},
{"learn":[4.981288914],"iteration":107,"passed_time":0.05188804892,"remaining_time":0.04420093056},
{"learn":[4.978186574],"iteration":108,"passed_time":0.05236465479,"remaining_time":0.0437172806},
{"learn":[4.967625033],"iteration":109,"passed_time":0.05286829853,"remaining_time":0.04325588062},
{"learn":[4.956265451],"iteration":110,"passed_time":0.05333627779,"remaining_time":0.04276512364},
{"learn":[4.951578499],"iteration":111,"passed_time":0.0537808916,"remaining_time":0.04225641483},
{"learn":[4.942381435],"iteration":112,"passed_time":0.05421184552,"remaining_time":0.04173832355},
{"learn":[4.938918782],"iteration":113,"passed_time":0.05463795807,"remaining_time":0.04121810872},
{"learn":[4.931482346],"iteration":114,"passed_time":0.05505736828,"remaining_time":0.04069457656},
{"learn":[4.92606844],"iteration":115,"passed_time":0.05547921091,"remaining_time":0.04017460101},
{"learn":[4.916412907],"iteration":116,"passed_time":0.05590843727,"remaining_time":0.03966154097},
{"learn":[4.908571163],"iteration":117,"passed_time":0.05639115859,"remaining_time":0.03918707631},
{"learn":[4.902958549],"iteration":118,"passed_time":0.05684555415,"remaining_time":0.03869319232},
{"learn":[4.897192424],"iteration":119,"passed_time":0.05733589157,"remaining_time":0.03822392771},
{"learn":[4.890863091],"iteration":120,"passed_time":0.05776593012,"remaining_time":0.03771494611},
{"learn":[4.884541769],"iteration":121,"passed_time":0.05819629555,"remaining_time":0.03720746765},
{"learn":[4.880692318],"iteration":122,"passed_time":0.0587800919,"remaining_time":0.03679729331},
{"learn":[4.874905756],"iteration":123,"passed_time":0.05926266248,"remaining_time":0.036322277},
{"learn":[4.865019252],"iteration":124,"passed_time":0.05985244571,"remaining_time":0.03591146743},
{"learn":[4.860679525],"iteration":125,"passed_time":0.06040220487,"remaining_time":0.0354743108},
{"learn":[4.85743514],"iteration":126,"passed_time":0.06091773592,"remaining_time":0.03501570647},
{"learn":[4.856732541],"iteration":127,"passed_time":0.06146623998,"remaining_time":0.03457475999},
{"learn":[4.852113329],"iteration":128,"passed_time":0.06200001291,"remaining_time":0.03412403811},
{"learn":[4.848165953],"iteration":129,"passed_time":0.06242969695,"remaining_time":0.03361599067},
{"learn":[4.843571583],"iteration":130,"passed_time":0.06288718221,"remaining_time":0.033123783},
{"learn":[4.839526339],"iteration":131,"passed_time":0.06340317513,"remaining_time":0.03266224173},
{"learn":[4.833106655],"iteration":132,"passed_time":0.06391807493,"remaining_time":0.03219933098},
{"learn":[4.820184543],"iteration":133,"passed_time":0.06439767247,"remaining_time":0.03171825659},
{"learn":[4.809510431],"iteration":134,"passed_time":0.06485379014,"remaining_time":0.03122589896},
{"learn":[4.805998087],"iteration":135,"passed_time":0.06533069814,"remaining_time":0.03074385795},
{"learn":[4.798736071],"iteration":136,"passed_time":0.06586196375,"remaining_time":0.03028688844},
{"learn":[4.794455092],"iteration":137,"passed_time":0.06631178663,"remaining_time":0.02979225196},
{"learn":[4.790975652],"iteration":138,"passed_time":0.06677238731,"remaining_time":0.02930299011},
{"learn":[4.782393596],"iteration":139,"passed_time":0.06727357934,"remaining_time":0.028831534},
{"learn":[4.776931167],"iteration":140,"passed_time":0.06776800894,"remaining_time":0.02835682644},
{"learn":[4.774357646],"iteration":141,"passed_time":0.0682667017,"remaining_time":0.02788358239},
{"learn":[4.768361127],"iteration":142,"passed_time":0.06867615628,"remaining_time":0.02737441194},
{"learn":[4.767776772],"iteration":143,"passed_time":0.06922085614,"remaining_time":0.02691922183},
{"learn":[4.759004841],"iteration":144,"passed_time":0.06963047045,"remaining_time":0.02641155776},
{"learn":[4.756706068],"iteration":145,"passed_time":0.07010996547,"remaining_time":0.02593108312},
{"learn":[4.74990655],"iteration":146,"passed_time":0.07067063292,"remaining_time":0.02547988806},
{"learn":[4.747582626],"iteration":147,"passed_time":0.07115768008,"remaining_time":0.02500134705},
{"learn":[4.740023083],"iteration":148,"passed_time":0.07163437691,"remaining_time":0.02451914914},
{"learn":[4.733858747],"iteration":149,"passed_time":0.07209552527,"remaining_time":0.02403184176},
{"learn":[4.727631942],"iteration":150,"passed_time":0.07251009506,"remaining_time":0.02352976595},
{"learn":[4.716973235],"iteration":151,"passed_time":0.07300050833,"remaining_time":0.0230527921},
{"learn":[4.709800368],"iteration":152,"passed_time":0.07342184699,"remaining_time":0.02255442359},
{"learn":[4.700664752],"iteration":153,"passed_time":0.07390592691,"remaining_time":0.02207579635},
{"learn":[4.690072007],"iteration":154,"passed_time":0.07438274587,"remaining_time":0.02159499074},
{"learn":[4.685239795],"iteration":155,"passed_time":0.07485455247,"remaining_time":0.02111282249},
{"learn":[4.678213586],"iteration":156,"passed_time":0.07535559376,"remaining_time":0.0206387932},
{"learn":[4.669276099],"iteration":157,"passed_time":0.07583096318,"remaining_time":0.02015759781},
{"learn":[4.668577527],"iteration":158,"passed_time":0.07623910961,"remaining_time":0.01965914147},
{"learn":[4.663900368],"iteration":159,"passed_time":0.07671103063,"remaining_time":0.01917775766},
{"learn":[4.654189851],"iteration":160,"passed_time":0.07720997442,"remaining_time":0.01870303728},
{"learn":[4.651402697],"iteration":161,"passed_time":0.07766595259,"remaining_time":0.0182179395},
{"learn":[4.648018049],"iteration":162,"passed_time":0.07810309942,"remaining_time":0.01772892441},
{"learn":[4.647584322],"iteration":163,"passed_time":0.07855699551,"remaining_time":0.01724421853},
{"learn":[4.643757951],"iteration":164,"passed_time":0.07899521875,"remaining_time":0.01675656155},
{"learn":[4.639819101],"iteration":165,"passed_time":0.07947095649,"remaining_time":0.01627718386},
{"learn":[4.636361724],"iteration":166,"passed_time":0.07992963064,"remaining_time":0.01579447791},
{"learn":[4.633127205],"iteration":167,"passed_time":0.08042927703,"remaining_time":0.01531986229},
{"learn":[4.6273391],"iteration":168,"passed_time":0.08085929148,"remaining_time":0.01483217773},
{"learn":[4.622427808],"iteration":169,"passed_time":0.08132081331,"remaining_time":0.01435073176},
{"learn":[4.619759141],"iteration":170,"passed_time":0.08175220307,"remaining_time":0.01386440871},
{"learn":[4.617659192],"iteration":171,"passed_time":0.08219815844,"remaining_time":0.01338109556},
{"learn":[4.609258302],"iteration":172,"passed_time":0.08265014086,"remaining_time":0.01289915493},
{"learn":[4.604065488],"iteration":173,"passed_time":0.08307262309,"remaining_time":0.01241315058},
{"learn":[4.59847434],"iteration":174,"passed_time":0.0835123653,"remaining_time":0.0119303379},
{"learn":[4.597857679],"iteration":175,"passed_time":0.08394831682,"remaining_time":0.01144749775},
{"learn":[4.594502197],"iteration":176,"passed_time":0.08448486254,"remaining_time":0.01097825897},
{"learn":[4.587435504],"iteration":177,"passed_time":0.08496195759,"remaining_time":0.01050091611},
{"learn":[4.579130018],"iteration":178,"passed_time":0.08544179941,"remaining_time":0.01002389825},
{"learn":[4.572011462],"iteration":179,"passed_time":0.08591742948,"remaining_time":0.009546381054},
{"learn":[4.569028119],"iteration":180,"passed_time":0.08635285678,"remaining_time":0.009064664524},
{"learn":[4.56487603],"iteration":181,"passed_time":0.08685391736,"remaining_time":0.008589947871},
{"learn":[4.55806884],"iteration":182,"passed_time":0.08732393532,"remaining_time":0.008112059565},
{"learn":[4.554485183],"iteration":183,"passed_time":0.0877412869,"remaining_time":0.007629677122},
{"learn":[4.551465476],"iteration":184,"passed_time":0.08818821196,"remaining_time":0.007150395564},
{"learn":[4.545503451],"iteration":185,"passed_time":0.08862921795,"remaining_time":0.006671016405},
{"learn":[4.537131065],"iteration":186,"passed_time":0.08908199168,"remaining_time":0.006192865732},
{"learn":[4.532154664],"iteration":187,"passed_time":0.08955238825,"remaining_time":0.005716109888},
{"learn":[4.526211612],"iteration":188,"passed_time":0.08996987258,"remaining_time":0.00523634179},
{"learn":[4.520530506],"iteration":189,"passed_time":0.09042817036,"remaining_time":0.004759377388},
{"learn":[4.516704286],"iteration":190,"passed_time":0.09091409002,"remaining_time":0.004283910001},
{"learn":[4.514655353],"iteration":191,"passed_time":0.09135340379,"remaining_time":0.003806391825},
{"learn":[4.511771725],"iteration":192,"passed_time":0.09177950027,"remaining_time":0.003328790165},
{"learn":[4.509724409],"iteration":193,"passed_time":0.09220394631,"remaining_time":0.002851668443},
{"learn":[4.501174654],"iteration":194,"passed_time":0.09272179279,"remaining_time":0.002377481866},
{"learn":[4.493711625],"iteration":195,"passed_time":0.09317749134,"remaining_time":0.001901581456},
{"learn":[4.486223878],"iteration":196,"passed_time":0.0936288123,"remaining_time":0.001425819477},
{"learn":[4.483091924],"iteration":197,"passed_time":0.09407888877,"remaining_time":0.0009502918058},
{"learn":[4.475583168],"iteration":198,"passed_time":0.09449136137,"remaining_time":0.0004748309617},
{"learn":[4.46977611],"iteration":199,"passed_time":0.09491773362,"remaining_time":0}
]}